serveitlearn/__init__.py
serveitlearn/__main__.py
serveitlearn/cli.py
serveitlearn/decorator.py
serveitlearn/py.typed
serveitlearn/serveitlearn/__init__.py
serveitlearn/serveitlearn/__main__.py
serveitlearn/serveitlearn/cli.py
serveitlearn/serveitlearn/decorator.py
serveitlearn/serveitlearn/py.typed
serveitlearn/serveitlearn.egg-info/PKG-INFO
serveitlearn/serveitlearn.egg-info/SOURCES.txt
serveitlearn/serveitlearn.egg-info/dependency_links.txt
serveitlearn/serveitlearn.egg-info/not-zip-safe
serveitlearn/serveitlearn.egg-info/requires.txt
serveitlearn/serveitlearn.egg-info/top_level.txt
tests/__init__.py
tests/test_serveitlearn.py
serveitlearn-0.1.1.dist-info/LICENSE
serveitlearn-0.1.1.dist-info/METADATA
serveitlearn-0.1.1.dist-info/WHEEL
serveitlearn-0.1.1.dist-info/top_level.txt
serveitlearn-0.1.1.dist-info/RECORD
