Metadata-Version: 2.1
Name: serveitlearn
Version: 0.1.1
Summary: Send a POST request to infer your ML model with FastAPI
Home-page: https://github.com/samarpan-rai/serveitlearn
Author: Samarpan Rai
Author-email: samarpan-rai@live.com
License: MIT license
Keywords: serveitlearn
Platform: UNKNOWN
Classifier: Development Status :: 2 - Pre-Alpha
Classifier: License :: OSI Approved :: MIT License
Classifier: Natural Language :: English
Classifier: Programming Language :: Python :: 3
Requires-Python: >=3.7
Requires-Dist: fastapi (==0.59.0)
Requires-Dist: requests
Requires-Dist: uvicorn (==0.11.5)
